adafruit_ccs811.py
adafruit_circuitpython_ccs811-1.3.22.dist-info/licenses/LICENSE
adafruit_circuitpython_ccs811-1.3.22.dist-info/METADATA
adafruit_circuitpython_ccs811-1.3.22.dist-info/WHEEL
adafruit_circuitpython_ccs811-1.3.22.dist-info/top_level.txt
adafruit_circuitpython_ccs811-1.3.22.dist-info/RECORD
